{"makespan": 568.32378, "n_tasks": 8, "n_robots": 3, "robot_schedules": {"0": [], "1": [{"task": 8, "start_time": 14.764823, "end_time": 87.764823}, {"task": 6, "start_time": 178.43455, "end_time": 261.43455}, {"task": 5, "start_time": 295.61057, "end_time": 364.61057}, {"task": 3, "start_time": 382.41506, "end_time": 474.41506}], "2": [{"task": 1, "start_time": 30.413813, "end_time": 113.413813}, {"task": 2, "start_time": 186.76911, "end_time": 251.76911}, {"task": 4, "start_time": 324.2191, "end_time": 383.2191}, {"task": 7, "start_time": 431.52023, "end_time": 517.5202300000001}]}}