{"makespan": 671.13735, "n_tasks": 8, "n_robots": 3, "robot_schedules": {"0": [{"task": 5, "start_time": 8.9442719, "end_time": 76.9442719}, {"task": 2, "start_time": 110.47038, "end_time": 201.47038}, {"task": 1, "start_time": 218.96324, "end_time": 304.96324000000004}, {"task": 3, "start_time": 358.45155, "end_time": 435.45155}, {"task": 8, "start_time": 447.65811, "end_time": 507.65811}, {"task": 6, "start_time": 585.88854, "end_time": 644.88854}], "1": [{"task": 4, "start_time": 70.0, "end_time": 148.0}, {"task": 1, "start_time": 218.96324, "end_time": 304.96324000000004}], "2": [{"task": 2, "start_time": 110.47038, "end_time": 201.47038}, {"task": 7, "start_time": 263.08207, "end_time": 336.08207}, {"task": 8, "start_time": 447.65811, "end_time": 507.65811}]}}