{"makespan": 541.24327, "n_tasks": 8, "n_robots": 3, "robot_schedules": {"0": [{"task": 7, "start_time": 56.0803, "end_time": 106.0803}, {"task": 1, "start_time": 120.0803, "end_time": 189.0803}], "1": [{"task": 7, "start_time": 56.0803, "end_time": 106.0803}, {"task": 1, "start_time": 120.0803, "end_time": 189.0803}, {"task": 4, "start_time": 267.99798, "end_time": 319.99798}, {"task": 5, "start_time": 337.02736, "end_time": 390.02736}, {"task": 8, "start_time": 405.02736, "end_time": 480.02736}], "2": [{"task": 3, "start_time": 101.82829, "end_time": 200.82828999999998}, {"task": 2, "start_time": 216.12535, "end_time": 277.12535}, {"task": 6, "start_time": 390.02736, "end_time": 467.02736}]}}