{"makespan": 478.69421, "n_tasks": 8, "n_robots": 3, "robot_schedules": {"0": [{"task": 1, "start_time": 49.203658, "end_time": 131.203658}, {"task": 7, "start_time": 196.39568, "end_time": 267.39567999999997}, {"task": 6, "start_time": 303.4512, "end_time": 396.4512}], "1": [{"task": 2, "start_time": 42.941821, "end_time": 132.941821}, {"task": 6, "start_time": 303.4512, "end_time": 396.4512}], "2": [{"task": 8, "start_time": 55.00909, "end_time": 129.00909000000001}, {"task": 4, "start_time": 143.87516, "end_time": 229.87516}, {"task": 3, "start_time": 276.69396, "end_time": 341.69396}, {"task": 5, "start_time": 387.23515, "end_time": 451.23515}]}}