{"makespan": 456.38166, "n_tasks": 8, "n_robots": 3, "robot_schedules": {"0": [{"task": 3, "start_time": 47.095647, "end_time": 121.095647}, {"task": 8, "start_time": 155.0515, "end_time": 210.0515}, {"task": 1, "start_time": 327.49477, "end_time": 425.49477}], "1": [{"task": 2, "start_time": 20.880613, "end_time": 98.880613}, {"task": 4, "start_time": 121.68412, "end_time": 183.68412}, {"task": 6, "start_time": 200.44718, "end_time": 285.44718}, {"task": 1, "start_time": 327.49477, "end_time": 425.49477}], "2": [{"task": 5, "start_time": 91.678787, "end_time": 190.678787}, {"task": 7, "start_time": 285.44718, "end_time": 355.44718}]}}