{"makespan": 587.6481, "n_tasks": 8, "n_robots": 3, "robot_schedules": {"0": [{"task": 4, "start_time": 111.40018, "end_time": 172.40018}], "1": [{"task": 1, "start_time": 97.621719, "end_time": 191.62171899999998}, {"task": 3, "start_time": 315.78362, "end_time": 414.78362}], "2": [{"task": 6, "start_time": 14.866069, "end_time": 112.866069}, {"task": 8, "start_time": 161.23962, "end_time": 234.23962}, {"task": 5, "start_time": 242.78362, "end_time": 315.78362000000004}, {"task": 7, "start_time": 353.51954, "end_time": 411.51954}, {"task": 2, "start_time": 500.87837, "end_time": 563.87837}]}}