{"makespan": 666.78387, "n_tasks": 8, "n_robots": 3, "robot_schedules": {"0": [{"task": 3, "start_time": 35.171011, "end_time": 114.171011}, {"task": 2, "start_time": 118.41365, "end_time": 181.41365000000002}, {"task": 5, "start_time": 191.85396, "end_time": 288.85396000000003}, {"task": 1, "start_time": 327.48037, "end_time": 395.48037}, {"task": 4, "start_time": 423.37303, "end_time": 481.37303}, {"task": 7, "start_time": 490.85986, "end_time": 587.85986}], "1": [{"task": 8, "start_time": 44.011362, "end_time": 131.011362}, {"task": 6, "start_time": 288.85396, "end_time": 340.85396}], "2": [{"task": 8, "start_time": 44.011362, "end_time": 131.011362}]}}