{"makespan": 793.58007, "n_tasks": 8, "n_robots": 3, "robot_schedules": {"0": [{"task": 4, "start_time": 5.0990195, "end_time": 82.0990195}, {"task": 2, "start_time": 156.15981, "end_time": 214.15981}, {"task": 6, "start_time": 280.16738, "end_time": 350.16738}, {"task": 8, "start_time": 360.79753, "end_time": 440.79753}, {"task": 1, "start_time": 546.26642, "end_time": 633.26642}, {"task": 3, "start_time": 702.33161, "end_time": 773.33161}], "1": [{"task": 4, "start_time": 5.0990195, "end_time": 82.0990195}, {"task": 5, "start_time": 382.72502, "end_time": 464.72502}, {"task": 7, "start_time": 501.77904, "end_time": 570.77904}, {"task": 3, "start_time": 702.33161, "end_time": 773.33161}], "2": [{"task": 2, "start_time": 156.15981, "end_time": 214.15981}, {"task": 6, "start_time": 280.16738, "end_time": 350.16738}, {"task": 5, "start_time": 382.72502, "end_time": 464.72502}, {"task": 1, "start_time": 546.26642, "end_time": 633.26642}]}}