{"makespan": 392.42479, "n_tasks": 8, "n_robots": 3, "robot_schedules": {"0": [{"task": 3, "start_time": 8.9442719, "end_time": 99.9442719}, {"task": 6, "start_time": 200.56051, "end_time": 272.56051}, {"task": 1, "start_time": 303.04001, "end_time": 374.04001}], "1": [{"task": 2, "start_time": 47.801674, "end_time": 98.80167399999999}, {"task": 5, "start_time": 123.56051, "end_time": 200.56051}, {"task": 7, "start_time": 286.65348, "end_time": 349.65348}], "2": [{"task": 8, "start_time": 84.148678, "end_time": 178.14867800000002}, {"task": 4, "start_time": 208.95452, "end_time": 306.95452}]}}