{"makespan": 513.82614, "n_tasks": 8, "n_robots": 3, "robot_schedules": {"0": [{"task": 2, "start_time": 79.511006, "end_time": 168.511006}, {"task": 7, "start_time": 209.5232, "end_time": 277.5232}, {"task": 3, "start_time": 321.53456, "end_time": 373.53456}, {"task": 1, "start_time": 390.08751, "end_time": 489.08751}], "1": [{"task": 5, "start_time": 28.178006, "end_time": 92.178006}, {"task": 4, "start_time": 106.49583, "end_time": 167.49583}, {"task": 8, "start_time": 217.14459, "end_time": 292.14459}, {"task": 6, "start_time": 374.36989, "end_time": 469.36989}], "2": []}}