{"makespan": 636.03407, "n_tasks": 8, "n_robots": 3, "robot_schedules": {"0": [{"task": 6, "start_time": 19.924859, "end_time": 88.924859}, {"task": 3, "start_time": 176.94758, "end_time": 259.94758}, {"task": 4, "start_time": 496.77436, "end_time": 587.77436}], "1": [{"task": 1, "start_time": 17.492856, "end_time": 81.492856}, {"task": 5, "start_time": 107.10535, "end_time": 185.10535}, {"task": 8, "start_time": 250.96126, "end_time": 327.96126000000004}, {"task": 2, "start_time": 402.77436, "end_time": 496.77436}, {"task": 7, "start_time": 527.79048, "end_time": 581.79048}], "2": [{"task": 4, "start_time": 496.77436, "end_time": 587.77436}]}}