{"makespan": 408.04371, "n_tasks": 8, "n_robots": 3, "robot_schedules": {"0": [{"task": 8, "start_time": 27.658633, "end_time": 98.658633}, {"task": 3, "start_time": 118.75838, "end_time": 201.75838}, {"task": 7, "start_time": 241.38161, "end_time": 336.38161}], "1": [{"task": 1, "start_time": 50.537115, "end_time": 146.537115}, {"task": 4, "start_time": 171.05242, "end_time": 252.05242}], "2": [{"task": 5, "start_time": 50.009999, "end_time": 140.009999}, {"task": 6, "start_time": 167.21294, "end_time": 245.21294}, {"task": 2, "start_time": 290.81996, "end_time": 387.81996}]}}