{"makespan": 640.75295, "n_tasks": 8, "n_robots": 3, "robot_schedules": {"0": [{"task": 1, "start_time": 51.312766, "end_time": 139.312766}], "1": [{"task": 3, "start_time": 26.305893, "end_time": 77.305893}, {"task": 4, "start_time": 261.37519, "end_time": 347.37519}, {"task": 8, "start_time": 348.37519, "end_time": 423.37519}], "2": [{"task": 5, "start_time": 30.675723, "end_time": 126.675723}, {"task": 6, "start_time": 172.16198, "end_time": 240.16198}, {"task": 4, "start_time": 261.37519, "end_time": 347.37519}, {"task": 7, "start_time": 398.53181, "end_time": 481.53181}, {"task": 2, "start_time": 530.57261, "end_time": 629.57261}]}}