{"makespan": 711.83231, "n_tasks": 8, "n_robots": 3, "robot_schedules": {"0": [{"task": 2, "start_time": 22.472205, "end_time": 93.472205}, {"task": 1, "start_time": 105.67876, "end_time": 158.67876}, {"task": 4, "start_time": 168.72864, "end_time": 254.72864}, {"task": 3, "start_time": 330.47162, "end_time": 424.47162}, {"task": 6, "start_time": 461.68721, "end_time": 558.68721}, {"task": 7, "start_time": 567.28954, "end_time": 656.28954}], "1": [{"task": 5, "start_time": 64.288413, "end_time": 144.288413}], "2": [{"task": 8, "start_time": 61.66036, "end_time": 154.66036}]}}