{"makespan": 500.64538, "n_tasks": 8, "n_robots": 3, "robot_schedules": {"0": [{"task": 1, "start_time": 48.600412, "end_time": 110.600412}, {"task": 6, "start_time": 191.6251, "end_time": 284.6251}], "1": [{"task": 8, "start_time": 41.10961, "end_time": 139.10961}, {"task": 4, "start_time": 355.84007, "end_time": 435.84007}], "2": [{"task": 2, "start_time": 17.720045, "end_time": 115.720045}, {"task": 7, "start_time": 156.82965, "end_time": 231.82965}, {"task": 3, "start_time": 279.84007, "end_time": 355.84007}, {"task": 5, "start_time": 391.19541, "end_time": 458.19541}]}}