{"makespan": 593.40762, "n_tasks": 8, "n_robots": 3, "robot_schedules": {"0": [], "1": [{"task": 7, "start_time": 90.426766, "end_time": 188.426766}, {"task": 2, "start_time": 213.74474, "end_time": 279.74474}, {"task": 3, "start_time": 365.30759, "end_time": 453.30759}, {"task": 4, "start_time": 507.43706, "end_time": 576.43706}], "2": [{"task": 5, "start_time": 50.119856, "end_time": 136.119856}, {"task": 8, "start_time": 193.9904, "end_time": 279.9904}, {"task": 6, "start_time": 297.45465, "end_time": 375.45465}, {"task": 1, "start_time": 419.86186, "end_time": 480.86186}]}}