{"makespan": 462.64736, "n_tasks": 8, "n_robots": 3, "robot_schedules": {"0": [{"task": 5, "start_time": 71.168813, "end_time": 168.168813}, {"task": 6, "start_time": 177.11309, "end_time": 256.11309}, {"task": 8, "start_time": 341.34807, "end_time": 422.34807}], "1": [{"task": 7, "start_time": 78.771822, "end_time": 151.771822}, {"task": 3, "start_time": 199.5735, "end_time": 281.57349999999997}, {"task": 8, "start_time": 341.34807, "end_time": 422.34807}], "2": [{"task": 4, "start_time": 83.216585, "end_time": 141.216585}, {"task": 1, "start_time": 188.25912, "end_time": 277.25912}, {"task": 2, "start_time": 394.64736, "end_time": 457.64736}]}}