{"makespan": 430.40448, "n_tasks": 8, "n_robots": 3, "robot_schedules": {"0": [{"task": 3, "start_time": 71.784399, "end_time": 122.784399}, {"task": 6, "start_time": 135.8228, "end_time": 217.8228}, {"task": 7, "start_time": 274.28518, "end_time": 363.28518}], "1": [{"task": 2, "start_time": 122.7844, "end_time": 200.7844}, {"task": 5, "start_time": 280.79065, "end_time": 348.79065}], "2": [{"task": 1, "start_time": 77.006493, "end_time": 167.006493}, {"task": 4, "start_time": 200.7844, "end_time": 269.7844}, {"task": 8, "start_time": 299.51654, "end_time": 376.51654}]}}