{"makespan": 557.42703, "n_tasks": 8, "n_robots": 3, "robot_schedules": {"0": [{"task": 6, "start_time": 176.65506, "end_time": 274.65506}], "1": [{"task": 5, "start_time": 37.589892, "end_time": 130.589892}, {"task": 6, "start_time": 176.65506, "end_time": 274.65506}, {"task": 8, "start_time": 303.72395, "end_time": 364.72395}, {"task": 2, "start_time": 421.0267, "end_time": 496.0267}], "2": [{"task": 1, "start_time": 38.948684, "end_time": 105.948684}, {"task": 3, "start_time": 131.24691, "end_time": 208.24691}, {"task": 4, "start_time": 283.67899, "end_time": 335.67899}, {"task": 7, "start_time": 385.44846, "end_time": 443.44846}]}}