{"makespan": 582.07219, "n_tasks": 8, "n_robots": 3, "robot_schedules": {"0": [{"task": 2, "start_time": 2.8284271, "end_time": 93.8284271}, {"task": 5, "start_time": 161.60748, "end_time": 237.60748}, {"task": 4, "start_time": 427.87052, "end_time": 480.87052}], "1": [], "2": [{"task": 3, "start_time": 64.938432, "end_time": 140.938432}, {"task": 1, "start_time": 162.96115, "end_time": 244.96115}, {"task": 6, "start_time": 268.98197, "end_time": 331.98197}, {"task": 8, "start_time": 349.87052, "end_time": 427.87052}, {"task": 7, "start_time": 449.24807, "end_time": 508.24807}]}}