{"makespan": 664.60338, "n_tasks": 8, "n_robots": 3, "robot_schedules": {"0": [{"task": 4, "start_time": 35.805028, "end_time": 86.805028}, {"task": 5, "start_time": 110.82585, "end_time": 208.82585}, {"task": 6, "start_time": 225.46917, "end_time": 307.46916999999996}, {"task": 1, "start_time": 338.33987, "end_time": 428.33987}, {"task": 3, "start_time": 469.44948, "end_time": 552.44948}, {"task": 7, "start_time": 569.47886, "end_time": 648.47886}], "1": [{"task": 2, "start_time": 462.33987, "end_time": 529.33987}, {"task": 8, "start_time": 552.44948, "end_time": 613.44948}], "2": [{"task": 4, "start_time": 35.805028, "end_time": 86.805028}, {"task": 5, "start_time": 110.82585, "end_time": 208.82585}, {"task": 1, "start_time": 338.33987, "end_time": 428.33987}, {"task": 2, "start_time": 462.33987, "end_time": 529.33987}]}}