{"makespan": 720.66882, "n_tasks": 8, "n_robots": 3, "robot_schedules": {"0": [{"task": 6, "start_time": 37.44329, "end_time": 130.44329}, {"task": 2, "start_time": 209.56345, "end_time": 299.56345}, {"task": 3, "start_time": 363.35217, "end_time": 451.35217}, {"task": 1, "start_time": 511.43544, "end_time": 582.43544}, {"task": 5, "start_time": 612.96412, "end_time": 708.96412}], "1": [{"task": 3, "start_time": 363.35217, "end_time": 451.35217}], "2": [{"task": 6, "start_time": 37.44329, "end_time": 130.44329}, {"task": 7, "start_time": 158.30007, "end_time": 238.30007}, {"task": 8, "start_time": 246.36232, "end_time": 339.36232}, {"task": 1, "start_time": 511.43544, "end_time": 582.43544}, {"task": 4, "start_time": 598.71426, "end_time": 696.71426}]}}