{"makespan": 620.67827, "n_tasks": 8, "n_robots": 3, "robot_schedules": {"0": [{"task": 7, "start_time": 12.727922, "end_time": 91.727922}, {"task": 4, "start_time": 166.6145, "end_time": 242.6145}, {"task": 8, "start_time": 264.70523, "end_time": 321.70523}, {"task": 3, "start_time": 394.14831, "end_time": 471.14831}, {"task": 5, "start_time": 549.14831, "end_time": 608.14831}], "1": [{"task": 2, "start_time": 321.70523, "end_time": 393.70523}], "2": [{"task": 1, "start_time": 43.829214, "end_time": 120.82921400000001}, {"task": 2, "start_time": 321.70523, "end_time": 393.70523}, {"task": 6, "start_time": 471.14831, "end_time": 549.14831}]}}