{"makespan": 781.70283, "n_tasks": 8, "n_robots": 3, "robot_schedules": {"0": [{"task": 5, "start_time": 76.059187, "end_time": 126.059187}, {"task": 1, "start_time": 145.26856, "end_time": 228.26856}, {"task": 6, "start_time": 267.21724, "end_time": 346.21724}, {"task": 3, "start_time": 369.02075, "end_time": 461.02075}, {"task": 4, "start_time": 491.10397, "end_time": 574.10397}, {"task": 8, "start_time": 604.56706, "end_time": 689.56706}], "1": [{"task": 2, "start_time": 42.801869, "end_time": 105.80186900000001}], "2": [{"task": 5, "start_time": 76.059187, "end_time": 126.059187}, {"task": 1, "start_time": 145.26856, "end_time": 228.26856}, {"task": 6, "start_time": 267.21724, "end_time": 346.21724}, {"task": 7, "start_time": 394.10252, "end_time": 481.10252}, {"task": 8, "start_time": 604.56706, "end_time": 689.56706}]}}