{"makespan": 484.76339, "n_tasks": 8, "n_robots": 3, "robot_schedules": {"0": [{"task": 2, "start_time": 18.384776, "end_time": 75.384776}, {"task": 4, "start_time": 129.09697, "end_time": 181.09697}, {"task": 1, "start_time": 258.80167, "end_time": 325.80167}], "1": [{"task": 2, "start_time": 18.384776, "end_time": 75.384776}, {"task": 5, "start_time": 181.09697, "end_time": 247.09697}, {"task": 1, "start_time": 258.80167, "end_time": 325.80167}], "2": [{"task": 7, "start_time": 22.135944, "end_time": 102.135944}, {"task": 3, "start_time": 173.82974, "end_time": 258.82974}, {"task": 8, "start_time": 282.08914, "end_time": 375.08914}, {"task": 6, "start_time": 388.08914, "end_time": 448.08914}]}}