{"makespan": 575.44525, "n_tasks": 8, "n_robots": 3, "robot_schedules": {"0": [{"task": 5, "start_time": 156.992, "end_time": 236.992}], "1": [{"task": 8, "start_time": 47.507894, "end_time": 133.507894}, {"task": 6, "start_time": 181.60155, "end_time": 259.60155}, {"task": 7, "start_time": 283.37128, "end_time": 365.37128}, {"task": 2, "start_time": 382.37128, "end_time": 470.37128}, {"task": 4, "start_time": 495.37128, "end_time": 548.3712800000001}], "2": [{"task": 1, "start_time": 42.047592, "end_time": 112.04759200000001}, {"task": 5, "start_time": 156.992, "end_time": 236.992}, {"task": 3, "start_time": 365.37128, "end_time": 458.37128}]}}