{"makespan": 438.41752, "n_tasks": 8, "n_robots": 3, "robot_schedules": {"0": [{"task": 6, "start_time": 51.312766, "end_time": 107.31276600000001}, {"task": 3, "start_time": 148.49529, "end_time": 220.49529}, {"task": 7, "start_time": 231.67563, "end_time": 297.67563}], "1": [{"task": 5, "start_time": 72.470684, "end_time": 136.470684}, {"task": 4, "start_time": 191.57967, "end_time": 279.57966999999996}, {"task": 2, "start_time": 315.09023, "end_time": 374.09023}], "2": [{"task": 6, "start_time": 51.312766, "end_time": 107.31276600000001}, {"task": 8, "start_time": 129.31277, "end_time": 211.31277}, {"task": 1, "start_time": 255.91097, "end_time": 307.91097}]}}