{"makespan": 570.82722, "n_tasks": 8, "n_robots": 3, "robot_schedules": {"0": [{"task": 5, "start_time": 5.0, "end_time": 100.0}, {"task": 1, "start_time": 153.15073, "end_time": 225.15073}, {"task": 7, "start_time": 267.58892, "end_time": 340.58892}, {"task": 2, "start_time": 373.14656, "end_time": 472.14656}, {"task": 4, "start_time": 515.82722, "end_time": 568.82722}], "1": [{"task": 8, "start_time": 46.389654, "end_time": 116.38965400000001}, {"task": 3, "start_time": 137.93031, "end_time": 210.93031}], "2": [{"task": 6, "start_time": 66.121101, "end_time": 157.121101}]}}