{"makespan": 741.16447, "n_tasks": 8, "n_robots": 3, "robot_schedules": {"0": [{"task": 2, "start_time": 174.00016, "end_time": 236.00016}, {"task": 8, "start_time": 294.24963, "end_time": 390.24963}, {"task": 7, "start_time": 569.66601, "end_time": 659.66601}], "1": [{"task": 4, "start_time": 71.281134, "end_time": 147.281134}], "2": [{"task": 6, "start_time": 35.608988, "end_time": 85.608988}, {"task": 2, "start_time": 174.00016, "end_time": 236.00016}, {"task": 5, "start_time": 300.47496, "end_time": 353.47496}, {"task": 3, "start_time": 370.50435, "end_time": 428.50435}, {"task": 1, "start_time": 451.82816, "end_time": 535.82816}, {"task": 7, "start_time": 569.66601, "end_time": 659.66601}]}}