{"makespan": 825.5334, "n_tasks": 8, "n_robots": 3, "robot_schedules": {"0": [{"task": 4, "start_time": 29.068884, "end_time": 85.068884}, {"task": 7, "start_time": 219.09482, "end_time": 295.09482}, {"task": 3, "start_time": 460.37856, "end_time": 510.37856}, {"task": 5, "start_time": 532.73924, "end_time": 586.73924}, {"task": 6, "start_time": 730.34335, "end_time": 783.34335}], "1": [], "2": [{"task": 4, "start_time": 29.068884, "end_time": 85.068884}, {"task": 2, "start_time": 145.99507, "end_time": 198.99507}, {"task": 7, "start_time": 219.09482, "end_time": 295.09482}, {"task": 8, "start_time": 341.78529, "end_time": 418.78529}, {"task": 3, "start_time": 460.37856, "end_time": 510.37856}, {"task": 5, "start_time": 532.73924, "end_time": 586.73924}, {"task": 1, "start_time": 617.33336, "end_time": 680.33336}, {"task": 6, "start_time": 730.34335, "end_time": 783.34335}]}}