{"makespan": 606.28042, "n_tasks": 8, "n_robots": 3, "robot_schedules": {"0": [{"task": 6, "start_time": 12.529964, "end_time": 69.529964}, {"task": 8, "start_time": 182.13991, "end_time": 274.13991}, {"task": 5, "start_time": 363.32511, "end_time": 413.32511}, {"task": 4, "start_time": 483.84461, "end_time": 549.84461}], "1": [{"task": 6, "start_time": 12.529964, "end_time": 69.529964}, {"task": 1, "start_time": 160.93018, "end_time": 223.93018}, {"task": 3, "start_time": 286.58, "end_time": 374.58}, {"task": 7, "start_time": 451.40398, "end_time": 532.40398}], "2": [{"task": 2, "start_time": 82.32861, "end_time": 142.32861}, {"task": 8, "start_time": 182.13991, "end_time": 274.13991}, {"task": 5, "start_time": 363.32511, "end_time": 413.32511}, {"task": 7, "start_time": 451.40398, "end_time": 532.40398}]}}