{"makespan": 635.86241, "n_tasks": 8, "n_robots": 3, "robot_schedules": {"0": [{"task": 3, "start_time": 3.0, "end_time": 94.0}, {"task": 1, "start_time": 127.42155, "end_time": 216.42155}, {"task": 7, "start_time": 285.68193, "end_time": 371.68193}, {"task": 4, "start_time": 421.77185, "end_time": 477.77185}, {"task": 6, "start_time": 530.84727, "end_time": 602.84727}], "1": [{"task": 5, "start_time": 112.36103, "end_time": 206.36103}, {"task": 4, "start_time": 421.77185, "end_time": 477.77185}, {"task": 6, "start_time": 530.84727, "end_time": 602.84727}], "2": [{"task": 2, "start_time": 94.0, "end_time": 144.0}, {"task": 8, "start_time": 206.96825, "end_time": 281.96825}]}}