{"makespan": 509.72979, "n_tasks": 8, "n_robots": 3, "robot_schedules": {"0": [{"task": 4, "start_time": 66.887966, "end_time": 119.887966}, {"task": 3, "start_time": 150.88797, "end_time": 201.88797}, {"task": 2, "start_time": 216.88797, "end_time": 269.88797}, {"task": 7, "start_time": 276.95903, "end_time": 355.95903}, {"task": 6, "start_time": 403.12894, "end_time": 486.12894}], "1": [{"task": 5, "start_time": 64.280635, "end_time": 156.28063500000002}], "2": [{"task": 1, "start_time": 119.88797, "end_time": 198.88797}, {"task": 8, "start_time": 292.08131, "end_time": 366.08131}]}}