{"makespan": 511.4879, "n_tasks": 8, "n_robots": 3, "robot_schedules": {"0": [{"task": 3, "start_time": 34.176015, "end_time": 108.176015}, {"task": 4, "start_time": 132.93485, "end_time": 225.93485}, {"task": 1, "start_time": 230.40699, "end_time": 303.40699}, {"task": 6, "start_time": 350.41762, "end_time": 447.41762}], "1": [{"task": 5, "start_time": 43.931765, "end_time": 113.931765}, {"task": 8, "start_time": 157.79519, "end_time": 216.79519}, {"task": 2, "start_time": 257.24269, "end_time": 316.24269}], "2": [{"task": 7, "start_time": 108.17601, "end_time": 173.17601000000002}]}}