{"makespan": 911.71526, "n_tasks": 8, "n_robots": 3, "robot_schedules": {"0": [{"task": 2, "start_time": 54.488531, "end_time": 124.488531}, {"task": 5, "start_time": 135.66887, "end_time": 211.66887}, {"task": 6, "start_time": 247.73825, "end_time": 315.73825}, {"task": 4, "start_time": 368.88898, "end_time": 437.88898}, {"task": 3, "start_time": 457.30547, "end_time": 528.30547}, {"task": 7, "start_time": 541.34387, "end_time": 617.34387}, {"task": 8, "start_time": 670.14539, "end_time": 758.14539}, {"task": 1, "start_time": 824.62847, "end_time": 888.62847}], "1": [], "2": []}}