{"makespan": 762.89545, "n_tasks": 8, "n_robots": 3, "robot_schedules": {"0": [{"task": 4, "start_time": 65.544004, "end_time": 145.544004}], "1": [], "2": [{"task": 3, "start_time": 8.5440037, "end_time": 65.5440037}, {"task": 6, "start_time": 86.639027, "end_time": 178.639027}, {"task": 2, "start_time": 209.23314, "end_time": 270.23314}, {"task": 7, "start_time": 307.11132, "end_time": 403.11132}, {"task": 8, "start_time": 421.35961, "end_time": 471.35961}, {"task": 1, "start_time": 508.48103, "end_time": 584.4810299999999}, {"task": 5, "start_time": 647.48897, "end_time": 713.48897}]}}