{"makespan": 483.16138, "n_tasks": 8, "n_robots": 3, "robot_schedules": {"0": [{"task": 4, "start_time": 39.560081, "end_time": 138.560081}, {"task": 1, "start_time": 192.93839, "end_time": 275.93839}, {"task": 5, "start_time": 316.24967, "end_time": 415.24967}], "1": [{"task": 7, "start_time": 57.008771, "end_time": 135.008771}, {"task": 3, "start_time": 223.7387, "end_time": 307.7387}], "2": [{"task": 8, "start_time": 49.244289, "end_time": 134.244289}, {"task": 2, "start_time": 208.44671, "end_time": 258.44671}, {"task": 6, "start_time": 292.28456, "end_time": 387.28456}]}}