{"makespan": 553.90788, "n_tasks": 8, "n_robots": 3, "robot_schedules": {"0": [{"task": 1, "start_time": 11.18034, "end_time": 62.18034}, {"task": 7, "start_time": 120.25787, "end_time": 198.25787}, {"task": 2, "start_time": 265.72639, "end_time": 350.72639}], "1": [{"task": 4, "start_time": 9.2195445, "end_time": 90.2195445}, {"task": 3, "start_time": 121.46054, "end_time": 179.46053999999998}, {"task": 8, "start_time": 223.02658, "end_time": 276.02657999999997}, {"task": 6, "start_time": 332.16926, "end_time": 428.16926}, {"task": 5, "start_time": 458.69794, "end_time": 515.69794}], "2": []}}