{"makespan": 778.47872, "n_tasks": 8, "n_robots": 3, "robot_schedules": {"0": [{"task": 5, "start_time": 60.60528, "end_time": 131.60528}, {"task": 2, "start_time": 438.87112, "end_time": 509.87112}, {"task": 1, "start_time": 532.34332, "end_time": 607.34332}], "1": [{"task": 5, "start_time": 60.60528, "end_time": 131.60528}, {"task": 4, "start_time": 146.02749, "end_time": 214.02749}, {"task": 6, "start_time": 241.48655, "end_time": 293.48654999999997}, {"task": 8, "start_time": 308.75088, "end_time": 384.75088}, {"task": 2, "start_time": 438.87112, "end_time": 509.87112}, {"task": 3, "start_time": 530.89492, "end_time": 586.89492}, {"task": 7, "start_time": 624.01634, "end_time": 722.01634}], "2": []}}