{"makespan": 411.35245, "n_tasks": 8, "n_robots": 3, "robot_schedules": {"0": [{"task": 5, "start_time": 68.007353, "end_time": 127.007353}, {"task": 6, "start_time": 148.84768, "end_time": 221.84768}, {"task": 1, "start_time": 255.3887, "end_time": 322.3887}], "1": [{"task": 5, "start_time": 68.007353, "end_time": 127.007353}, {"task": 8, "start_time": 137.6375, "end_time": 211.6375}, {"task": 2, "start_time": 280.25965, "end_time": 341.25965}], "2": [{"task": 3, "start_time": 95.0, "end_time": 178.0}, {"task": 4, "start_time": 213.90265, "end_time": 271.90265}, {"task": 7, "start_time": 285.90265, "end_time": 348.90265}]}}