{"makespan": 518.92361, "n_tasks": 8, "n_robots": 3, "robot_schedules": {"0": [{"task": 6, "start_time": 82.006097, "end_time": 136.006097}, {"task": 4, "start_time": 380.30631, "end_time": 477.30631}], "1": [{"task": 5, "start_time": 3.0, "end_time": 69.0}, {"task": 1, "start_time": 115.2277, "end_time": 177.2277}, {"task": 8, "start_time": 210.24285, "end_time": 267.24285}, {"task": 2, "start_time": 316.6392, "end_time": 370.6392}, {"task": 7, "start_time": 420.28797, "end_time": 490.28797}], "2": [{"task": 5, "start_time": 3.0, "end_time": 69.0}, {"task": 8, "start_time": 210.24285, "end_time": 267.24285}, {"task": 3, "start_time": 330.30631, "end_time": 380.30631}, {"task": 7, "start_time": 420.28797, "end_time": 490.28797}]}}