{"makespan": 749.79109, "n_tasks": 8, "n_robots": 3, "robot_schedules": {"0": [{"task": 8, "start_time": 70.349129, "end_time": 135.349129}, {"task": 5, "start_time": 161.76882, "end_time": 243.76882}], "1": [{"task": 3, "start_time": 67.052218, "end_time": 163.05221799999998}, {"task": 6, "start_time": 211.2186, "end_time": 288.21860000000004}, {"task": 7, "start_time": 348.12686, "end_time": 446.12686}, {"task": 4, "start_time": 463.15625, "end_time": 530.15625}, {"task": 2, "start_time": 566.17013, "end_time": 634.17013}, {"task": 1, "start_time": 656.73116, "end_time": 724.73116}], "2": []}}