{"makespan": 571.51422, "n_tasks": 8, "n_robots": 3, "robot_schedules": {"0": [{"task": 7, "start_time": 12.649111, "end_time": 94.649111}, {"task": 5, "start_time": 156.39051, "end_time": 241.39051}], "1": [{"task": 1, "start_time": 29.154759, "end_time": 98.154759}, {"task": 8, "start_time": 137.75274, "end_time": 221.75274}], "2": [{"task": 1, "start_time": 29.154759, "end_time": 98.154759}, {"task": 4, "start_time": 140.30924, "end_time": 224.30924}, {"task": 3, "start_time": 283.77351, "end_time": 336.77351}, {"task": 6, "start_time": 369.02254, "end_time": 445.02254}, {"task": 2, "start_time": 495.11246, "end_time": 560.11246}]}}