{"makespan": 581.65982, "n_tasks": 8, "n_robots": 3, "robot_schedules": {"0": [{"task": 8, "start_time": 37.48333, "end_time": 119.48333}, {"task": 2, "start_time": 173.0837, "end_time": 225.0837}, {"task": 4, "start_time": 259.91185, "end_time": 314.91185}, {"task": 5, "start_time": 328.36548, "end_time": 412.36548}, {"task": 3, "start_time": 474.10687, "end_time": 565.1068700000001}], "1": [{"task": 8, "start_time": 37.48333, "end_time": 119.48333}, {"task": 6, "start_time": 130.88508, "end_time": 184.88508}, {"task": 3, "start_time": 474.10687, "end_time": 565.1068700000001}], "2": [{"task": 7, "start_time": 50.0, "end_time": 107.0}, {"task": 2, "start_time": 173.0837, "end_time": 225.0837}, {"task": 1, "start_time": 296.30168, "end_time": 367.30168}]}}