{"makespan": 522.91466, "n_tasks": 8, "n_robots": 3, "robot_schedules": {"0": [{"task": 8, "start_time": 79.120162, "end_time": 136.120162}], "1": [{"task": 5, "start_time": 85.146932, "end_time": 135.146932}, {"task": 3, "start_time": 177.25394, "end_time": 263.25394}, {"task": 7, "start_time": 292.37438, "end_time": 385.37438}, {"task": 1, "start_time": 389.84651, "end_time": 456.84651}], "2": [{"task": 6, "start_time": 60.90156, "end_time": 131.90156000000002}, {"task": 4, "start_time": 164.55122, "end_time": 257.55122}, {"task": 2, "start_time": 300.27123, "end_time": 391.27123}]}}