{"makespan": 623.68339, "n_tasks": 8, "n_robots": 3, "robot_schedules": {"0": [{"task": 1, "start_time": 127.84542, "end_time": 203.84542}, {"task": 3, "start_time": 295.08138, "end_time": 359.08138}, {"task": 8, "start_time": 363.20448, "end_time": 436.20448}, {"task": 2, "start_time": 510.89049, "end_time": 595.89049}], "1": [{"task": 6, "start_time": 62.625873, "end_time": 118.625873}, {"task": 1, "start_time": 127.84542, "end_time": 203.84542}, {"task": 3, "start_time": 295.08138, "end_time": 359.08138}, {"task": 8, "start_time": 363.20448, "end_time": 436.20448}, {"task": 5, "start_time": 473.84754, "end_time": 562.84754}], "2": [{"task": 7, "start_time": 118.62587, "end_time": 213.62587000000002}, {"task": 4, "start_time": 287.7339, "end_time": 378.7339}, {"task": 2, "start_time": 510.89049, "end_time": 595.89049}]}}