{"makespan": 716.47287, "n_tasks": 8, "n_robots": 3, "robot_schedules": {"0": [{"task": 7, "start_time": 613.77489, "end_time": 684.77489}], "1": [{"task": 4, "start_time": 46.097722, "end_time": 145.097722}, {"task": 8, "start_time": 186.72704, "end_time": 283.72704}, {"task": 3, "start_time": 442.09335, "end_time": 499.09335}, {"task": 6, "start_time": 517.77489, "end_time": 613.77489}, {"task": 5, "start_time": 632.15966, "end_time": 697.15966}], "2": [{"task": 1, "start_time": 70.035705, "end_time": 143.035705}, {"task": 2, "start_time": 283.72704, "end_time": 347.72704}, {"task": 3, "start_time": 442.09335, "end_time": 499.09335}, {"task": 6, "start_time": 517.77489, "end_time": 613.77489}, {"task": 5, "start_time": 632.15966, "end_time": 697.15966}]}}