{"makespan": 489.65682, "n_tasks": 8, "n_robots": 3, "robot_schedules": {"0": [{"task": 2, "start_time": 295.25716, "end_time": 369.25716}], "1": [{"task": 8, "start_time": 32.015621, "end_time": 101.01562100000001}, {"task": 7, "start_time": 134.25716, "end_time": 213.25716}, {"task": 3, "start_time": 228.29046, "end_time": 288.29046}, {"task": 1, "start_time": 375.52577, "end_time": 470.52577}], "2": [{"task": 5, "start_time": 87.286586, "end_time": 179.286586}, {"task": 4, "start_time": 213.25716, "end_time": 295.25716}, {"task": 6, "start_time": 319.58821, "end_time": 387.58821}]}}