{"makespan": 550.33651, "n_tasks": 8, "n_robots": 3, "robot_schedules": {"0": [{"task": 1, "start_time": 61.911227, "end_time": 128.911227}, {"task": 4, "start_time": 151.93296, "end_time": 224.93296}, {"task": 5, "start_time": 272.19816, "end_time": 339.19816}, {"task": 3, "start_time": 437.137, "end_time": 510.137}], "1": [{"task": 2, "start_time": 21.260292, "end_time": 107.26029199999999}, {"task": 7, "start_time": 160.29801, "end_time": 227.29801}], "2": [{"task": 1, "start_time": 61.911227, "end_time": 128.911227}, {"task": 8, "start_time": 170.14228, "end_time": 258.14228}, {"task": 6, "start_time": 332.60704, "end_time": 424.60704}, {"task": 3, "start_time": 437.137, "end_time": 510.137}]}}