{"makespan": 735.19122, "n_tasks": 8, "n_robots": 3, "robot_schedules": {"0": [], "1": [{"task": 6, "start_time": 18.027756, "end_time": 70.027756}, {"task": 7, "start_time": 115.30468, "end_time": 175.30468000000002}], "2": [{"task": 5, "start_time": 37.589892, "end_time": 128.589892}, {"task": 8, "start_time": 137.80944, "end_time": 213.80944}, {"task": 3, "start_time": 240.88341, "end_time": 331.88341}, {"task": 1, "start_time": 388.31921, "end_time": 485.31921}, {"task": 2, "start_time": 529.50066, "end_time": 616.50066}, {"task": 4, "start_time": 632.62517, "end_time": 691.62517}]}}