{"makespan": 574.88607, "n_tasks": 8, "n_robots": 3, "robot_schedules": {"0": [{"task": 2, "start_time": 17.029386, "end_time": 86.029386}, {"task": 7, "start_time": 90.152492, "end_time": 161.152492}, {"task": 6, "start_time": 314.36542, "end_time": 367.36542}], "1": [{"task": 5, "start_time": 72.443081, "end_time": 159.443081}, {"task": 3, "start_time": 234.44308, "end_time": 304.44308}, {"task": 1, "start_time": 391.55219, "end_time": 462.55219}, {"task": 8, "start_time": 483.64721, "end_time": 549.64721}], "2": [{"task": 2, "start_time": 17.029386, "end_time": 86.029386}, {"task": 7, "start_time": 90.152492, "end_time": 161.152492}, {"task": 4, "start_time": 215.4848, "end_time": 293.4848}, {"task": 6, "start_time": 314.36542, "end_time": 367.36542}, {"task": 1, "start_time": 391.55219, "end_time": 462.55219}, {"task": 8, "start_time": 483.64721, "end_time": 549.64721}]}}