{"makespan": 408.01445, "n_tasks": 8, "n_robots": 3, "robot_schedules": {"0": [{"task": 5, "start_time": 48.548944, "end_time": 137.548944}, {"task": 3, "start_time": 188.03657, "end_time": 252.03657}, {"task": 6, "start_time": 300.08862, "end_time": 381.08862}], "1": [{"task": 4, "start_time": 8.0622577, "end_time": 78.0622577}, {"task": 7, "start_time": 140.04613, "end_time": 207.04613}, {"task": 2, "start_time": 230.89985, "end_time": 318.89985}], "2": [{"task": 1, "start_time": 21.633308, "end_time": 115.633308}, {"task": 8, "start_time": 252.03657, "end_time": 307.03657}]}}