{"makespan": 545.18718, "n_tasks": 8, "n_robots": 3, "robot_schedules": {"0": [{"task": 8, "start_time": 87.206651, "end_time": 147.206651}, {"task": 7, "start_time": 209.2389, "end_time": 283.2389}, {"task": 2, "start_time": 328.88975, "end_time": 385.88975}, {"task": 5, "start_time": 423.90291, "end_time": 516.90291}], "1": [], "2": [{"task": 4, "start_time": 10.77033, "end_time": 61.77033}, {"task": 6, "start_time": 109.93671, "end_time": 184.93671}, {"task": 3, "start_time": 255.96487, "end_time": 332.96487}, {"task": 1, "start_time": 385.88975, "end_time": 463.88975}]}}