{"makespan": 721.11633, "n_tasks": 8, "n_robots": 3, "robot_schedules": {"0": [{"task": 5, "start_time": 65.490457, "end_time": 120.490457}, {"task": 8, "start_time": 134.52613, "end_time": 226.52613}, {"task": 1, "start_time": 262.92668, "end_time": 336.92668}, {"task": 6, "start_time": 405.95566, "end_time": 488.95566}, {"task": 3, "start_time": 511.31633, "end_time": 571.31633}, {"task": 2, "start_time": 582.71809, "end_time": 675.71809}], "1": [{"task": 8, "start_time": 134.52613, "end_time": 226.52613}, {"task": 7, "start_time": 272.22076, "end_time": 360.22076}, {"task": 4, "start_time": 369.44031, "end_time": 421.44031}, {"task": 3, "start_time": 511.31633, "end_time": 571.31633}, {"task": 2, "start_time": 582.71809, "end_time": 675.71809}], "2": [{"task": 5, "start_time": 65.490457, "end_time": 120.490457}, {"task": 8, "start_time": 134.52613, "end_time": 226.52613}, {"task": 7, "start_time": 272.22076, "end_time": 360.22076}]}}