{"makespan": 626.26483, "n_tasks": 8, "n_robots": 3, "robot_schedules": {"0": [{"task": 6, "start_time": 39.812058, "end_time": 102.81205800000001}, {"task": 5, "start_time": 178.05168, "end_time": 264.05168000000003}, {"task": 3, "start_time": 378.62177, "end_time": 477.62177}, {"task": 7, "start_time": 516.45474, "end_time": 592.45474}], "1": [{"task": 8, "start_time": 248.02003, "end_time": 320.02003}], "2": [{"task": 6, "start_time": 39.812058, "end_time": 102.81205800000001}, {"task": 4, "start_time": 163.02003, "end_time": 248.02003}, {"task": 2, "start_time": 269.60706, "end_time": 344.60706}, {"task": 3, "start_time": 378.62177, "end_time": 477.62177}, {"task": 1, "start_time": 490.62177, "end_time": 588.62177}]}}