{"makespan": 501.18575, "n_tasks": 8, "n_robots": 3, "robot_schedules": {"0": [{"task": 3, "start_time": 76.837491, "end_time": 137.837491}, {"task": 6, "start_time": 172.24679, "end_time": 260.24679000000003}, {"task": 5, "start_time": 298.57433, "end_time": 348.57433}, {"task": 2, "start_time": 365.33869, "end_time": 429.33869}], "1": [{"task": 1, "start_time": 84.864598, "end_time": 136.864598}, {"task": 7, "start_time": 170.16625, "end_time": 230.16625}, {"task": 4, "start_time": 314.33869, "end_time": 365.33869}, {"task": 8, "start_time": 380.57024, "end_time": 439.57024}], "2": [{"task": 3, "start_time": 76.837491, "end_time": 137.837491}, {"task": 6, "start_time": 172.24679, "end_time": 260.24679000000003}, {"task": 5, "start_time": 298.57433, "end_time": 348.57433}, {"task": 2, "start_time": 365.33869, "end_time": 429.33869}]}}