{"makespan": 903.47496, "n_tasks": 8, "n_robots": 3, "robot_schedules": {"0": [{"task": 2, "start_time": 30.675723, "end_time": 89.675723}, {"task": 6, "start_time": 110.55634, "end_time": 190.55634}, {"task": 3, "start_time": 234.65849, "end_time": 288.65849000000003}, {"task": 1, "start_time": 344.02093, "end_time": 415.02093}, {"task": 5, "start_time": 497.02703, "end_time": 592.02703}, {"task": 8, "start_time": 649.06211, "end_time": 701.06211}, {"task": 7, "start_time": 719.31039, "end_time": 775.31039}, {"task": 4, "start_time": 810.23889, "end_time": 901.23889}], "1": [], "2": []}}