{"makespan": 647.49179, "n_tasks": 8, "n_robots": 3, "robot_schedules": {"0": [{"task": 3, "start_time": 24.839485, "end_time": 116.839485}, {"task": 2, "start_time": 125.38349, "end_time": 205.38349}, {"task": 8, "start_time": 448.64441, "end_time": 518.64441}], "1": [{"task": 5, "start_time": 314.85569, "end_time": 392.85569}, {"task": 7, "start_time": 417.06313, "end_time": 490.06313}], "2": [{"task": 3, "start_time": 24.839485, "end_time": 116.839485}, {"task": 2, "start_time": 125.38349, "end_time": 205.38349}, {"task": 4, "start_time": 227.85569, "end_time": 314.85569}, {"task": 1, "start_time": 353.33946, "end_time": 417.33946}, {"task": 8, "start_time": 448.64441, "end_time": 518.64441}, {"task": 6, "start_time": 538.86816, "end_time": 595.86816}]}}