{"makespan": 669.56429, "n_tasks": 8, "n_robots": 3, "robot_schedules": {"0": [{"task": 1, "start_time": 71.0, "end_time": 143.0}, {"task": 8, "start_time": 193.93133, "end_time": 262.93133}, {"task": 2, "start_time": 309.79282, "end_time": 395.79282}, {"task": 7, "start_time": 418.79282, "end_time": 483.79282}, {"task": 4, "start_time": 541.77558, "end_time": 605.77558}], "1": [{"task": 2, "start_time": 309.79282, "end_time": 395.79282}, {"task": 4, "start_time": 541.77558, "end_time": 605.77558}], "2": [{"task": 3, "start_time": 62.39391, "end_time": 145.39391}, {"task": 5, "start_time": 216.45726, "end_time": 293.45726}, {"task": 6, "start_time": 393.88136, "end_time": 461.88136}]}}