{"makespan": 798.64079, "n_tasks": 8, "n_robots": 3, "robot_schedules": {"0": [{"task": 7, "start_time": 577.78827, "end_time": 657.78827}], "1": [{"task": 3, "start_time": 657.78827, "end_time": 731.78827}], "2": [{"task": 2, "start_time": 3.1622777, "end_time": 101.1622777}, {"task": 1, "start_time": 181.93975, "end_time": 238.93975}, {"task": 4, "start_time": 317.09984, "end_time": 406.09984}, {"task": 6, "start_time": 487.78827, "end_time": 577.78827}, {"task": 5, "start_time": 600.9831, "end_time": 651.9831}, {"task": 8, "start_time": 694.04258, "end_time": 754.04258}]}}