{"makespan": 672.74421, "n_tasks": 8, "n_robots": 3, "robot_schedules": {"0": [{"task": 7, "start_time": 55.443665, "end_time": 126.44366500000001}, {"task": 4, "start_time": 131.82883, "end_time": 194.82883}, {"task": 8, "start_time": 215.44436, "end_time": 287.44435999999996}, {"task": 3, "start_time": 310.53115, "end_time": 401.53115}, {"task": 6, "start_time": 451.62107, "end_time": 531.6210699999999}, {"task": 1, "start_time": 538.02419, "end_time": 630.02419}], "1": [{"task": 5, "start_time": 287.44436, "end_time": 360.44436}], "2": [{"task": 7, "start_time": 55.443665, "end_time": 126.44366500000001}, {"task": 4, "start_time": 131.82883, "end_time": 194.82883}, {"task": 8, "start_time": 215.44436, "end_time": 287.44435999999996}, {"task": 2, "start_time": 311.52755, "end_time": 409.52755}, {"task": 1, "start_time": 538.02419, "end_time": 630.02419}]}}