{"makespan": 464.53324, "n_tasks": 8, "n_robots": 3, "robot_schedules": {"0": [{"task": 3, "start_time": 68.117545, "end_time": 160.117545}, {"task": 7, "start_time": 236.07148, "end_time": 324.07148}, {"task": 6, "start_time": 396.98924, "end_time": 455.98924}], "1": [{"task": 4, "start_time": 83.240615, "end_time": 172.240615}, {"task": 1, "start_time": 237.43264, "end_time": 327.43264}, {"task": 6, "start_time": 396.98924, "end_time": 455.98924}], "2": [{"task": 5, "start_time": 61.983869, "end_time": 149.983869}, {"task": 2, "start_time": 186.12249, "end_time": 261.12248999999997}, {"task": 8, "start_time": 303.92436, "end_time": 390.92436}]}}