{"makespan": 605.49888, "n_tasks": 8, "n_robots": 3, "robot_schedules": {"0": [{"task": 1, "start_time": 82.462113, "end_time": 173.462113}, {"task": 7, "start_time": 234.00136, "end_time": 309.00136}], "1": [{"task": 6, "start_time": 72.470684, "end_time": 169.470684}, {"task": 2, "start_time": 194.20932, "end_time": 256.20932}, {"task": 8, "start_time": 302.78184, "end_time": 392.78184}, {"task": 5, "start_time": 470.67921, "end_time": 555.67921}], "2": [{"task": 3, "start_time": 78.0, "end_time": 131.0}, {"task": 4, "start_time": 187.0803, "end_time": 243.0803}]}}