{"makespan": 485.1047, "n_tasks": 8, "n_robots": 3, "robot_schedules": {"0": [{"task": 8, "start_time": 86.400231, "end_time": 139.40023100000002}, {"task": 4, "start_time": 155.89265, "end_time": 210.89265}, {"task": 7, "start_time": 288.68726, "end_time": 381.68726}, {"task": 5, "start_time": 417.82588, "end_time": 468.82588}], "1": [{"task": 8, "start_time": 86.400231, "end_time": 139.40023100000002}, {"task": 4, "start_time": 155.89265, "end_time": 210.89265}, {"task": 2, "start_time": 221.89265, "end_time": 293.89265}, {"task": 3, "start_time": 341.52668, "end_time": 401.52668}], "2": [{"task": 1, "start_time": 76.026311, "end_time": 130.02631100000002}, {"task": 6, "start_time": 151.02631, "end_time": 216.02631}]}}