{"makespan": 832.50399, "n_tasks": 8, "n_robots": 3, "robot_schedules": {"0": [{"task": 3, "start_time": 19.0, "end_time": 118.0}, {"task": 8, "start_time": 127.48683, "end_time": 199.48683}, {"task": 1, "start_time": 482.60036, "end_time": 546.60036}], "1": [{"task": 5, "start_time": 339.77455, "end_time": 393.77455}, {"task": 2, "start_time": 611.63112, "end_time": 680.63112}], "2": [{"task": 3, "start_time": 19.0, "end_time": 118.0}, {"task": 8, "start_time": 127.48683, "end_time": 199.48683}, {"task": 6, "start_time": 228.7614, "end_time": 301.7614}, {"task": 5, "start_time": 339.77455, "end_time": 393.77455}, {"task": 7, "start_time": 417.18395, "end_time": 469.18395}, {"task": 1, "start_time": 482.60036, "end_time": 546.60036}, {"task": 2, "start_time": 611.63112, "end_time": 680.63112}, {"task": 4, "start_time": 711.04493, "end_time": 805.04493}]}}