{"makespan": 600.04892, "n_tasks": 8, "n_robots": 3, "robot_schedules": {"0": [{"task": 4, "start_time": 242.36674, "end_time": 324.36674}, {"task": 8, "start_time": 469.7731, "end_time": 523.7731}], "1": [{"task": 1, "start_time": 31.144823, "end_time": 102.144823}, {"task": 5, "start_time": 183.36674, "end_time": 242.36674}, {"task": 7, "start_time": 247.46576, "end_time": 314.46576}, {"task": 3, "start_time": 343.74032, "end_time": 408.74032}, {"task": 8, "start_time": 469.7731, "end_time": 523.7731}], "2": [{"task": 2, "start_time": 63.56886, "end_time": 158.56886}, {"task": 6, "start_time": 408.74032, "end_time": 477.74032}]}}