{"makespan": 635.82714, "n_tasks": 8, "n_robots": 3, "robot_schedules": {"0": [{"task": 5, "start_time": 35.805028, "end_time": 95.805028}], "1": [{"task": 1, "start_time": 14.035669, "end_time": 108.035669}, {"task": 8, "start_time": 118.03567, "end_time": 198.03566999999998}, {"task": 6, "start_time": 214.16018, "end_time": 280.16017999999997}, {"task": 7, "start_time": 331.89992, "end_time": 426.89992}, {"task": 2, "start_time": 526.36348, "end_time": 577.36348}], "2": [{"task": 1, "start_time": 14.035669, "end_time": 108.035669}, {"task": 8, "start_time": 118.03567, "end_time": 198.03566999999998}, {"task": 4, "start_time": 241.41769, "end_time": 293.41769}, {"task": 7, "start_time": 331.89992, "end_time": 426.89992}, {"task": 3, "start_time": 446.1353, "end_time": 527.1352999999999}]}}