{"makespan": 536.14621, "n_tasks": 8, "n_robots": 3, "robot_schedules": {"0": [{"task": 2, "start_time": 69.375788, "end_time": 165.375788}, {"task": 8, "start_time": 202.05003, "end_time": 298.05003}, {"task": 3, "start_time": 318.29849, "end_time": 401.29849}], "1": [], "2": [{"task": 1, "start_time": 24.083189, "end_time": 80.083189}, {"task": 5, "start_time": 134.4247, "end_time": 195.4247}, {"task": 6, "start_time": 213.45246, "end_time": 303.45246}, {"task": 4, "start_time": 342.6698, "end_time": 410.6698}, {"task": 7, "start_time": 435.6698, "end_time": 509.6698}]}}