{"makespan": 503.73989, "n_tasks": 8, "n_robots": 3, "robot_schedules": {"0": [{"task": 8, "start_time": 2.0, "end_time": 67.0}, {"task": 6, "start_time": 70.162278, "end_time": 123.162278}, {"task": 4, "start_time": 193.25507, "end_time": 252.25507}, {"task": 5, "start_time": 279.45801, "end_time": 354.45801}, {"task": 7, "start_time": 407.28627, "end_time": 490.28627}], "1": [{"task": 2, "start_time": 207.19879, "end_time": 295.19879000000003}], "2": [{"task": 8, "start_time": 2.0, "end_time": 67.0}, {"task": 3, "start_time": 110.13931, "end_time": 165.13931}, {"task": 2, "start_time": 207.19879, "end_time": 295.19879000000003}, {"task": 1, "start_time": 334.82202, "end_time": 389.82202}, {"task": 7, "start_time": 407.28627, "end_time": 490.28627}]}}