{"makespan": 639.59508, "n_tasks": 8, "n_robots": 3, "robot_schedules": {"0": [{"task": 3, "start_time": 26.019224, "end_time": 88.01922400000001}, {"task": 6, "start_time": 131.03085, "end_time": 217.03085}, {"task": 4, "start_time": 277.57009, "end_time": 352.57009}, {"task": 7, "start_time": 366.71223, "end_time": 422.71223}, {"task": 8, "start_time": 494.82325, "end_time": 560.8232499999999}], "1": [{"task": 2, "start_time": 56.356011, "end_time": 143.356011}, {"task": 7, "start_time": 366.71223, "end_time": 422.71223}, {"task": 8, "start_time": 494.82325, "end_time": 560.8232499999999}], "2": [{"task": 5, "start_time": 88.019224, "end_time": 143.019224}, {"task": 1, "start_time": 209.41952, "end_time": 262.41952000000003}]}}