{"makespan": 354.87119, "n_tasks": 8, "n_robots": 3, "robot_schedules": {"0": [{"task": 2, "start_time": 53.235327, "end_time": 124.235327}, {"task": 6, "start_time": 150.31214, "end_time": 211.31214}, {"task": 1, "start_time": 215.78427, "end_time": 285.78427}], "1": [{"task": 5, "start_time": 39.408121, "end_time": 111.408121}, {"task": 7, "start_time": 179.43753, "end_time": 268.43753000000004}], "2": [{"task": 8, "start_time": 49.658836, "end_time": 140.658836}, {"task": 4, "start_time": 166.2127, "end_time": 219.2127}, {"task": 3, "start_time": 270.69085, "end_time": 343.69085}]}}