{"makespan": 765.46375, "n_tasks": 8, "n_robots": 3, "robot_schedules": {"0": [{"task": 2, "start_time": 10.049876, "end_time": 93.049876}, {"task": 5, "start_time": 198.31145, "end_time": 261.31145000000004}, {"task": 8, "start_time": 326.77137, "end_time": 384.77137}, {"task": 1, "start_time": 406.97497, "end_time": 491.97497}], "1": [{"task": 2, "start_time": 10.049876, "end_time": 93.049876}, {"task": 5, "start_time": 198.31145, "end_time": 261.31145000000004}, {"task": 6, "start_time": 280.95834, "end_time": 338.95834}, {"task": 3, "start_time": 389.55478, "end_time": 465.55478}, {"task": 4, "start_time": 513.82485, "end_time": 603.82485}, {"task": 7, "start_time": 655.22524, "end_time": 719.22524}], "2": []}}