{"makespan": 664.75984, "n_tasks": 8, "n_robots": 3, "robot_schedules": {"0": [{"task": 6, "start_time": 86.977008, "end_time": 170.977008}], "1": [{"task": 3, "start_time": 15.620499, "end_time": 91.620499}, {"task": 1, "start_time": 160.99629, "end_time": 213.99629}, {"task": 4, "start_time": 236.35697, "end_time": 298.35697}, {"task": 2, "start_time": 345.17577, "end_time": 422.17577}, {"task": 5, "start_time": 442.17577, "end_time": 495.17577}, {"task": 8, "start_time": 543.43548, "end_time": 621.43548}], "2": [{"task": 3, "start_time": 15.620499, "end_time": 91.620499}, {"task": 2, "start_time": 345.17577, "end_time": 422.17577}, {"task": 7, "start_time": 503.56987, "end_time": 565.56987}]}}