{"makespan": 512.22091, "n_tasks": 8, "n_robots": 3, "robot_schedules": {"0": [{"task": 2, "start_time": 47.042534, "end_time": 142.042534}, {"task": 7, "start_time": 184.09013, "end_time": 245.09013}, {"task": 4, "start_time": 287.13772, "end_time": 341.13772}, {"task": 6, "start_time": 373.27804, "end_time": 455.27804}], "1": [{"task": 8, "start_time": 40.112342, "end_time": 125.112342}, {"task": 5, "start_time": 147.20306, "end_time": 235.20306}, {"task": 1, "start_time": 249.13145, "end_time": 325.13145}, {"task": 3, "start_time": 374.49743, "end_time": 454.49743}], "2": [{"task": 8, "start_time": 40.112342, "end_time": 125.112342}, {"task": 1, "start_time": 249.13145, "end_time": 325.13145}]}}