{"makespan": 635.17342, "n_tasks": 8, "n_robots": 3, "robot_schedules": {"0": [{"task": 3, "start_time": 41.10961, "end_time": 140.10961}, {"task": 7, "start_time": 236.71706, "end_time": 300.71706}, {"task": 5, "start_time": 366.33718, "end_time": 456.33718}], "1": [{"task": 8, "start_time": 112.89502, "end_time": 210.89502}, {"task": 1, "start_time": 300.71706, "end_time": 352.71706}, {"task": 4, "start_time": 456.33718, "end_time": 525.33718}], "2": [{"task": 6, "start_time": 86.977008, "end_time": 162.977008}, {"task": 7, "start_time": 236.71706, "end_time": 300.71706}, {"task": 2, "start_time": 366.72464, "end_time": 455.72464}]}}