{"makespan": 875.83781, "n_tasks": 8, "n_robots": 3, "robot_schedules": {"0": [], "1": [{"task": 3, "start_time": 34.0, "end_time": 111.0}, {"task": 7, "start_time": 169.66856, "end_time": 233.66856}, {"task": 1, "start_time": 285.2922, "end_time": 363.2922}, {"task": 5, "start_time": 395.18264, "end_time": 486.18264}, {"task": 8, "start_time": 507.44293, "end_time": 600.4429299999999}, {"task": 6, "start_time": 645.75297, "end_time": 726.75297}, {"task": 2, "start_time": 779.83781, "end_time": 870.83781}], "2": [{"task": 4, "start_time": 486.18264, "end_time": 565.18264}]}}