{"makespan": 827.96662, "n_tasks": 8, "n_robots": 3, "robot_schedules": {"0": [], "1": [], "2": [{"task": 8, "start_time": 52.952809, "end_time": 112.952809}, {"task": 3, "start_time": 146.96751, "end_time": 218.96751}, {"task": 2, "start_time": 225.05027, "end_time": 289.05027}, {"task": 5, "start_time": 306.51452, "end_time": 402.51452}, {"task": 7, "start_time": 422.21224, "end_time": 499.21224}, {"task": 6, "start_time": 513.14063, "end_time": 601.14063}, {"task": 4, "start_time": 669.73363, "end_time": 738.73363}, {"task": 1, "start_time": 760.93723, "end_time": 810.93723}]}}